[{"pid": 58966, "position": "relief", "name": "Tom Nicol", "win": 0, "loss": 0, "earned_runs": 0, "unearned_runs": 0, "innings_pitched": 4.999999999999999, "pitches_thrown": 105, "balls": 35, "strikes": 55, "walks": 0, "strikeouts": 9, "homeruns": 0, "triples": 0, "doubles": 0, "singles": 0, "hbp": 0, "ibb": 0, "wildpitches": 0, "balks": 0, "games_started": 0, "appearances": 0, "era": 0.0, "hits_allowed": 0, "whip": 0.0, "fip": -3.6}, {"pid": 43617, "position": "starter", "name": "Darrion Smith", "win": 0, "loss": 0, "earned_runs": 0, "unearned_runs": 0, "innings_pitched": 4.333333333333333, "pitches_thrown": 101, "balls": 31, "strikes": 48, "walks": 0, "strikeouts": 8, "homeruns": 0, "triples": 0, "doubles": 0, "singles": 0, "hbp": 0, "ibb": 0, "wildpitches": 0, "balks": 0, "games_started": 0, "appearances": 0, "era": 0.0, "hits_allowed": 0, "whip": 0.0, "fip": -3.692}, {"pid": 50579, "position": "relief", "name": "David Gillery", "win": 0, "loss": 0, "earned_runs": 0, "unearned_runs": 0, "innings_pitched": 2.6666666666666665, "pitches_thrown": 25, "balls": 3, "strikes": 13, "walks": 0, "strikeouts": 3, "homeruns": 0, "triples": 0, "doubles": 0, "singles": 0, "hbp": 0, "ibb": 0, "wildpitches": 0, "balks": 0, "games_started": 0, "appearances": 0, "era": 0.0, "hits_allowed": 0, "whip": 0.0, "fip": -2.25}]