[{"pid": 52697, "position": "starter", "name": "Neal Asiodu", "win": 0, "loss": 0, "earned_runs": 0, "unearned_runs": 0, "innings_pitched": 7.33333333333333, "pitches_thrown": 102, "balls": 21, "strikes": 51, "walks": 0, "strikeouts": 10, "homeruns": 0, "triples": 0, "doubles": 0, "singles": 0, "hbp": 0, "ibb": 0, "wildpitches": 0, "balks": 0, "games_started": 0, "appearances": 0, "era": 0.0, "hits_allowed": 0, "whip": 0.0, "fip": -2.727}, {"pid": 55136, "position": "relief", "name": "Kerry Barnhardt", "win": 0, "loss": 0, "earned_runs": 0, "unearned_runs": 0, "innings_pitched": 4.666666666666666, "pitches_thrown": 81, "balls": 32, "strikes": 30, "walks": 0, "strikeouts": 6, "homeruns": 0, "triples": 0, "doubles": 0, "singles": 0, "hbp": 0, "ibb": 0, "wildpitches": 0, "balks": 0, "games_started": 0, "appearances": 0, "era": 0.0, "hits_allowed": 0, "whip": 0.0, "fip": -2.571}]